stdx/__init__.py
stdx-0.0.0.dist-info/LICENSE
stdx-0.0.0.dist-info/WHEEL
stdx-0.0.0.dist-info/METADATA
stdx-0.0.0.dist-info/RECORD
