Metadata-Version: 2.1
Name: stdx
Version: 0.0.0
Summary: StdX is a comprehensive library of standard extensions for Python, designed to enhance the core language with additional utilities and functionality.
Author-email: Yuan-Kui Li <toregenerate@gmail.com>
Classifier: License :: OSI Approved :: MIT License
Project-URL: Home, https://github.com/djosix/python-stdx
